README.rst
setup.cfg
setup.py
scripts/unittest2canopsis
unittest2canopsis/__init__.py
unittest2canopsis/connector.py
unittest2canopsis/daemon.py
unittest2canopsis.egg-info/PKG-INFO
unittest2canopsis.egg-info/SOURCES.txt
unittest2canopsis.egg-info/dependency_links.txt
unittest2canopsis.egg-info/requires.txt
unittest2canopsis.egg-info/top_level.txt