Metadata-Version: 1.1
Name: unittest2canopsis
Version: 0.2
Summary: Canopsis Connector which generate events from unittest
Home-page: https://github.com/linkdd/unittest2canopsis
Author: David Delassus
Author-email: david.jose.delassus@gmail.com
License: MIT
Download-URL: https://github.com/linkdd/unittest2canopsis/tarball/0.1
Keywords: canopsis,unittest
Platform: UNKNOWN
